config/__init__.py
config/endpoints.py
helpers/__init__.py
helpers/utility.py
magiceden_solana/__init__.py
magiceden_solana/collections.py
magiceden_solana/instructions.py
magiceden_solana/launchpad.py
magiceden_solana/tokens.py
magiceden_solana/wallets.py
magiceden_solana-0.0.2.dist-info/LICENSE
magiceden_solana-0.0.2.dist-info/METADATA
magiceden_solana-0.0.2.dist-info/WHEEL
magiceden_solana-0.0.2.dist-info/top_level.txt
magiceden_solana-0.0.2.dist-info/RECORD
