Metadata-Version: 2.1
Name: magiceden_solana
Version: 0.0.2
Summary: Python SDK for interacting with the Magiceden Official APIs at https://api.magiceden.dev/
Home-page: https://github.com/vmpyre/magiceden_solana
Author: vmpyre.sol#0001 (Discord)
Author-email: vmpyrestax@gmail.com
Project-URL: Bug Tracker, https://github.com/vmpyre/magiceden_solana/issues
Classifier: Programming Language :: Python :: 3
Classifier: License :: OSI Approved :: MIT License
Classifier: Operating System :: OS Independent
Requires-Python: >=3.8
License-File: LICENSE
